npt/__init__.py
npt/_db.py
npt/_log.py
npt/_version.py
npt/cli.py
npt/datasets/__init__.py
npt/download/__init__.py
npt/download/_pds.py
npt/isis/__init__.py
npt/isis/_docker.py
npt/isis/_sh.py
npt/isis/calibration.py
npt/isis/format.py
npt/isis/mosaic.py
npt/isis/projection.py
npt/mosaic/__init__.py
npt/pipelines/__init__.py
npt/reduce/__init__.py
npt/search/__init__.py
npt/search/_ode.py
npt/utils/__init__.py
npt/utils/_gdal.py
npt/utils/_rasterio.py
npt/utils/_xarray.py
npt/utils/bbox.py
npt/utils/download.py
npt/utils/filenames.py
npt/utils/formatters.py
npt/utils/geojson.py
npt/utils/raster.py
npt/utils/tmpdir.py
npt-0.8.1.dist-info/LICENSE.txt
npt-0.8.1.dist-info/METADATA
npt-0.8.1.dist-info/WHEEL
npt-0.8.1.dist-info/entry_points.txt
npt-0.8.1.dist-info/top_level.txt
npt-0.8.1.dist-info/RECORD
